{
  "services": [
    {
      "region": "USA (DHL)",
      "type": "Duty Unpaid",
      "destinations": [
        {
          "name": "USA (DHL)",
          "tat": "6-8 DAYS",
          "rates": {
            "6": 1492.7,
            "7": 1427.8,
            "8": 1362.9,
            "9": 1298,
            "10": 1296.9,
            "11": 1296.9,
            "16": 1296.9
          }
        }
      ]
    },
    {
      "region": "Canada (DHL)",
      "type": "Duty Unpaid",
      "destinations": [
        { "name": "Canada (DHL)", "tat": "8-10 DAYS", "rates": { "6": 1357, "7": 1298, "8": 1239, "9": 1180, "10": 1179, "11": 1179, "16": 1179 } }
      ]
    },
    {
      "region": "Rest of Europe (DHL)",
      "type": "Duty Unpaid",
      "destinations": [
        { "name": "Rest of Europe (DHL)", "tat": "12-15 DAYS", "rates": { "6": 1003, "7": 974, "8": 944, "9": 915, "10": 885, "11": 885, "16": 856 } }
      ]
    },
    {
      "region": "Australia/New Zealand (DHL)",
      "type": "Duty Unpaid",
      "destinations": [
        { "name": "Australia/New Zealand (DHL)", "tat": "10-12 DAYS", "rates": { "6": 1328, "7": 1298, "8": 1239, "9": 1180, "10": 1179, "11": 1151, "16": 1121 } }
      ]
    },
    {
      "region": "USA",
      "type": "Duty Paid",
      "destinations": [
        {
          "name": "USA - Zones 2-5",
          "states": ["Connecticut", "District of Columbia", "New Jersey", "New York", "Rhode Island", "Delaware", "Massachusetts", "Maryland", "North Carolina", "Pennsylvania", "Virginia", "Maine", "Michigan", "Ohio", "South Carolina", "Vermont", "Alabama", "Florida", "Georgia", "Illinois", "Indiana", "Kentucky", "Missouri", "Tennessee", "Wisconsin"],
          "tat": "10-12 DAYS",
          "rates": {
            "6": 1426.7,
            "7": 1395.9,
            "8": 1362.9,
            "9": 1331,
            "10": 1331,
            "11": 1296.9,
            "16": 1233.1
          }
        },
        {
          "name": "USA - Zones 6-7",
          "states": ["Iowa", "Kansas", "Minnesota", "North Dakota", "Nebraska", "South Dakota", "Arkansas", "Colorado", "Louisiana", "Oklahoma", "Texas", "Wyoming"],
          "tat": "12-14 DAYS",
          "rates": {
            "6": 1492.7,
            "7": 1492.7,
            "8": 1460.8,
            "9": 1427.8,
            "10": 1427.8,
            "11": 1362.9,
            "16": 1296.9
          }
        },
        {
          "name": "USA - Zone 8",
          "states": ["Arizona", "California", "Idaho", "Montana", "New Mexico", "Nevada", "Oregon", "Utah", "Washington"],
          "tat": "12-16 DAYS",
          "rates": {
            "6": 1556.5,
            "7": 1525.7,
            "8": 1492.7,
            "9": 1479.5,
            "10": 1479.5,
            "11": 1426.7,
            "16": 1395.9
          }
        }
      ]
    },
    {
        "region": "UK",
        "type": "Duty Paid",
        "destinations": [
            { "name": "UK", "tat": "6-8 DAYS", "rates": { "6": 767, "7": 738, "8": 708, "9": 679, "10": 649, "11": 649, "16": 620 } }
        ]
    },
    {
      "region": "Europe",
      "type": "Duty Paid",
      "destinations": [
        { "name": "Austria", "tat": "10-12 Days", "lowWeight": { "base": 1885, "addl": 357.5 }, "rates": { "6": 897, "8": 858, "11": 793, "16": 760.5, "21": 741, "26": 728 } },
        { "name": "Belgium", "tat": "10-12 Days", "lowWeight": { "base": 1885, "addl": 357.5 }, "rates": { "6": 897, "8": 858, "11": 793, "16": 760.5, "21": 741, "26": 728 } },
        { "name": "Bulgaria", "tat": "10-12 Days", "lowWeight": { "base": 2210, "addl": 390 }, "rates": { "6": 1053, "8": 975, "11": 890.5, "16": 871, "21": 864.5, "26": 858 } },
        { "name": "Croatia", "tat": "10-12 Days", "lowWeight": { "base": 1885, "addl": 390 }, "rates": { "6": 988, "8": 884, "11": 825.5, "16": 780, "21": 780, "26": 767 } },
        { "name": "Czech Republic", "tat": "10-12 Days", "lowWeight": { "base": 1885, "addl": 390 }, "rates": { "6": 988, "8": 884, "11": 825.5, "16": 780, "21": 780, "26": 767 } },
        { "name": "Denmark", "tat": "10-12 Days", "lowWeight": { "base": 1885, "addl": 390 }, "rates": { "6": 988, "8": 884, "11": 825.5, "16": 780, "21": 780, "26": 767 } },
        { "name": "Estonia", "tat": "10-12 Days", "lowWeight": { "base": 2210, "addl": 390 }, "rates": { "6": 1053, "8": 975, "11": 890.5, "16": 871, "21": 864.5, "26": 851.5 } },
        { "name": "Finland", "tat": "10-12 Days", "lowWeight": { "base": 2210, "addl": 390 }, "rates": { "6": 1053, "8": 975, "11": 890.5, "16": 871, "21": 864.5, "26": 851.5 } },
        { "name": "France", "tat": "10-12 Days", "lowWeight": { "base": 1885, "addl": 357.5 }, "rates": { "6": 897, "8": 858, "11": 793, "16": 760.5, "21": 741, "26": 721.5 } },
        { "name": "Germany", "tat": "10-12 Days", "lowWeight": { "base": 1885, "addl": 325 }, "rates": { "6": 858, "8": 793, "11": 760.5, "16": 741, "21": 728, "26": 721.5 } },
        { "name": "Greece", "tat": "10-12 Days", "lowWeight": { "base": 2210, "addl": 390 }, "rates": { "6": 1053, "8": 975, "11": 890.5, "16": 741, "21": 864.5, "26": 851.5 } },
        { "name": "Hungary", "tat": "10-12 Days", "lowWeight": { "base": 1885, "addl": 390 }, "rates": { "6": 988, "8": 884, "11": 825.5, "16": 780, "21": 780, "26": 767 } },
        { "name": "Ireland", "tat": "10-12 Days", "lowWeight": { "base": 1885, "addl": 390 }, "rates": { "6": 988, "8": 884, "11": 825.5, "16": 780, "21": 780, "26": 767 } },
        { "name": "Italy", "tat": "10-12 Days", "lowWeight": { "base": 1885, "addl": 390 }, "rates": { "6": 988, "8": 884, "11": 825.5, "16": 780, "21": 780, "26": 767 } },
        { "name": "Latvia", "tat": "10-12 Days", "lowWeight": { "base": 1885, "addl": 390 }, "rates": { "6": 988, "8": 884, "11": 825.5, "16": 780, "21": 780, "26": 767 } },
        { "name": "Lithuania", "tat": "10-12 Days", "lowWeight": { "base": 1885, "addl": 390 }, "rates": { "6": 988, "8": 884, "11": 825.5, "16": 780, "21": 780, "26": 767 } },
        { "name": "Luxembourg", "tat": "10-12 Days", "lowWeight": { "base": 1885, "addl": 357.5 }, "rates": { "6": 897, "8": 858, "11": 793, "16": 760.5, "21": 741, "26": 721.5 } },
        { "name": "Monaco", "tat": "10-12 Days", "lowWeight": { "base": 1885, "addl": 357.5 }, "rates": { "6": 897, "8": 858, "11": 793, "16": 760.5, "21": 741, "26": 721.5 } },
        { "name": "Netherlands", "tat": "10-12 Days", "lowWeight": { "base": 1885, "addl": 357.5 }, "rates": { "6": 897, "8": 858, "11": 793, "16": 760.5, "21": 741, "26": 721.5 } },
        { "name": "Poland", "tat": "10-12 Days", "lowWeight": { "base": 1885, "addl": 357.5 }, "rates": { "6": 897, "8": 858, "11": 793, "16": 760.5, "21": 741, "26": 721.5 } },
        { "name": "Portugal", "tat": "10-12 Days", "lowWeight": { "base": 1885, "addl": 357.5 }, "rates": { "6": 897, "8": 858, "11": 793, "16": 760.5, "21": 741, "26": 721.5 } },
        { "name": "Romania", "tat": "10-12 Days", "lowWeight": { "base": 2210, "addl": 390 }, "rates": { "6": 1053, "8": 975, "11": 890.5, "16": 871, "21": 864.5, "26": 851.5 } },
        { "name": "Slovakia", "tat": "10-12 Days", "lowWeight": { "base": 1885, "addl": 390 }, "rates": { "6": 988, "8": 884, "11": 825.5, "16": 780, "21": 780, "26": 767 } },
        { "name": "Slovenia", "tat": "10-12 Days", "lowWeight": { "base": 1885, "addl": 357.5 }, "rates": { "6": 897, "8": 858, "11": 793, "16": 760.5, "21": 741, "26": 721.5 } },
        { "name": "Spain", "tat": "10-12 Days", "lowWeight": { "base": 1885, "addl": 390 }, "rates": { "6": 988, "8": 884, "11": 793, "16": 780, "21": 780, "26": 767 } },
        { "name": "Sweden", "tat": "10-12 Days", "lowWeight": { "base": 2210, "addl": 390 }, "rates": { "6": 1053, "8": 975, "11": 890.5, "16": 871, "21": 864.5, "26": 851.5 } }
      ]
    }
  ]
}
